[{"id": "266696", "name": "C Gallagher", "position": "M", "displayName": "Conor Gallagher", "jersey": "23", "citizen": "ENG", "stats": {"general": {"foulsCommitted": 55.0, "foulsSuffered": 37.0, "redCards": 1.0, "yellowCards": 6.0, "ownGoals": 0.0, "appearances": 26.0, "subIns": 0.0}, "offensive": {"goalAssists": 4.0, "offsides": 5.0, "shotsOnTarget": 11.0, "totalShots": 32.0, "totalGoals": 2.0}}, "salary": 6500}, {"id": "231718", "name": "A Disasi", "position": "D", "displayName": "Axel Disasi", "jersey": "2", "citizen": "FRA", "stats": {"general": {"foulsCommitted": 13.0, "foulsSuffered": 16.0, "redCards": 0.0, "yellowCards": 6.0, "ownGoals": 1.0, "appearances": 25.0, "subIns": 0.0}, "offensive": {"goalAssists": 0.0, "offsides": 5.0, "shotsOnTarget": 5.0, "totalShots": 13.0, "totalGoals": 2.0}}, "salary": 6200}, {"id": "156366", "name": "R Sterling", "position": "F", "displayName": "Raheem Sterling", "jersey": "7", "citizen": "ENG", "stats": {"general": {"foulsCommitted": 26.0, "foulsSuffered": 37.0, "redCards": 0.0, "yellowCards": 6.0, "ownGoals": 0.0, "appearances": 25.0, "subIns": 4.0}, "offensive": {"goalAssists": 3.0, "offsides": 5.0, "shotsOnTarget": 15.0, "totalShots": 42.0, "totalGoals": 6.0}}, "salary": 6700}, {"id": "285450", "name": "E Fern\u00e1ndez", "position": "M", "displayName": "Enzo Fern\u00e1ndez", "jersey": "8", "citizen": "ARG", "stats": {"general": {"foulsCommitted": 27.0, "foulsSuffered": 30.0, "redCards": 0.0, "yellowCards": 6.0, "ownGoals": 0.0, "appearances": 24.0, "subIns": 2.0}, "offensive": {"goalAssists": 2.0, "offsides": 14.0, "shotsOnTarget": 11.0, "totalShots": 39.0, "totalGoals": 3.0}}, "salary": 6500}, {"id": "289877", "name": "M Caicedo", "position": "M", "displayName": "Mois\u00e9s Caicedo", "jersey": "25", "citizen": "ECU", "stats": {"general": {"foulsCommitted": 41.0, "foulsSuffered": 30.0, "redCards": 0.0, "yellowCards": 8.0, "ownGoals": 0.0, "appearances": 24.0, "subIns": 2.0}, "offensive": {"goalAssists": 1.0, "offsides": 6.0, "shotsOnTarget": 1.0, "totalShots": 7.0, "totalGoals": 0.0}}, "salary": 6500}, {"id": "296395", "name": "C Palmer", "position": "M", "displayName": "Cole Palmer", "jersey": "20", "citizen": "ENG", "stats": {"general": {"foulsCommitted": 14.0, "foulsSuffered": 16.0, "redCards": 0.0, "yellowCards": 7.0, "ownGoals": 0.0, "appearances": 24.0, "subIns": 5.0}, "offensive": {"goalAssists": 8.0, "offsides": 7.0, "shotsOnTarget": 22.0, "totalShots": 56.0, "totalGoals": 11.0}}, "salary": 6500}, {"id": "308524", "name": "N Jackson", "position": "F", "displayName": "Nicolas Jackson", "jersey": "15", "citizen": "SEN", "stats": {"general": {"foulsCommitted": 15.0, "foulsSuffered": 21.0, "redCards": 0.0, "yellowCards": 9.0, "ownGoals": 0.0, "appearances": 24.0, "subIns": 4.0}, "offensive": {"goalAssists": 3.0, "offsides": 0.0, "shotsOnTarget": 23.0, "totalShots": 51.0, "totalGoals": 9.0}}, "salary": 6700}, {"id": "96254", "name": "T Silva", "position": "D", "displayName": "Thiago Silva", "jersey": "6", "citizen": "BRA", "stats": {"general": {"foulsCommitted": 7.0, "foulsSuffered": 8.0, "redCards": 0.0, "yellowCards": 3.0, "ownGoals": 0.0, "appearances": 23.0, "subIns": 1.0}, "offensive": {"goalAssists": 0.0, "offsides": 1.0, "shotsOnTarget": 3.0, "totalShots": 9.0, "totalGoals": 2.0}}, "salary": 6200}, {"id": "296410", "name": "L Colwill", "position": "D", "displayName": "Levi Colwill", "jersey": "26", "citizen": "ENG", "stats": {"general": {"foulsCommitted": 25.0, "foulsSuffered": 13.0, "redCards": 0.0, "yellowCards": 2.0, "ownGoals": 0.0, "appearances": 23.0, "subIns": 3.0}, "offensive": {"goalAssists": 1.0, "offsides": 4.0, "shotsOnTarget": 3.0, "totalShots": 11.0, "totalGoals": 1.0}}, "salary": 6200}, {"id": "299911", "name": "M Mudryk", "position": "M", "displayName": "Mykhailo Mudryk", "jersey": "10", "citizen": "UKR", "stats": {"general": {"foulsCommitted": 15.0, "foulsSuffered": 16.0, "redCards": 0.0, "yellowCards": 3.0, "ownGoals": 0.0, "appearances": 21.0, "subIns": 12.0}, "offensive": {"goalAssists": 2.0, "offsides": 5.0, "shotsOnTarget": 5.0, "totalShots": 15.0, "totalGoals": 4.0}}, "salary": 6300}, {"id": "308947", "name": "M Gusto", "position": "D", "displayName": "Malo Gusto", "jersey": "27", "citizen": "FRA", "stats": {"general": {"foulsCommitted": 17.0, "foulsSuffered": 23.0, "redCards": 1.0, "yellowCards": 5.0, "ownGoals": 0.0, "appearances": 20.0, "subIns": 5.0}, "offensive": {"goalAssists": 5.0, "offsides": 3.0, "shotsOnTarget": 0.0, "totalShots": 7.0, "totalGoals": 0.0}}, "salary": 5700}, {"id": "108662", "name": "R S\u00e1nchez", "position": "G", "displayName": "Robert S\u00e1nchez", "jersey": "1", "citizen": "ESP", "stats": {"general": {"foulsCommitted": 0.0, "foulsSuffered": 0.0, "redCards": 0.0, "yellowCards": 2.0, "ownGoals": 0.0, "appearances": 16.0, "subIns": 0.0}, "offensive": {"goalAssists": 0.0, "offsides": 2.0, "shotsOnTarget": 0.0, "totalShots": 0.0, "totalGoals": 0.0}}, "salary": 5300}, {"id": "289824", "name": "D Petrovic", "position": "G", "displayName": "Djordje Petrovic", "jersey": "28", "citizen": "SBA", "stats": {"general": {"foulsCommitted": 0.0, "foulsSuffered": 0.0, "redCards": 0.0, "yellowCards": 2.0, "ownGoals": 0.0, "appearances": 12.0, "subIns": 1.0}, "offensive": {"goalAssists": 0.0, "offsides": 2.0, "shotsOnTarget": 0.0, "totalShots": 0.0, "totalGoals": 0.0}}, "salary": 5300}, {"id": "225426", "name": "B Chilwell", "position": "D", "displayName": "Ben Chilwell", "jersey": "21", "citizen": "ENG", "stats": {"general": {"foulsCommitted": 10.0, "foulsSuffered": 12.0, "redCards": 0.0, "yellowCards": 5.0, "ownGoals": 0.0, "appearances": 12.0, "subIns": 3.0}, "offensive": {"goalAssists": 1.0, "offsides": 5.0, "shotsOnTarget": 3.0, "totalShots": 12.0, "totalGoals": 0.0}}, "salary": 5700}, {"id": "293236", "name": "N Madueke", "position": "F", "displayName": "Noni Madueke", "jersey": "11", "citizen": "ENG", "stats": {"general": {"foulsCommitted": 7.0, "foulsSuffered": 7.0, "redCards": 0.0, "yellowCards": 1.0, "ownGoals": 0.0, "appearances": 12.0, "subIns": 8.0}, "offensive": {"goalAssists": 0.0, "offsides": 2.0, "shotsOnTarget": 4.0, "totalShots": 9.0, "totalGoals": 2.0}}, "salary": 6000}, {"id": "259910", "name": "M Cucurella", "position": "D", "displayName": "Marc Cucurella", "jersey": "3", "citizen": "ESP", "stats": {"general": {"foulsCommitted": 12.0, "foulsSuffered": 11.0, "redCards": 0.0, "yellowCards": 5.0, "ownGoals": 0.0, "appearances": 10.0, "subIns": 1.0}, "offensive": {"goalAssists": 0.0, "offsides": 0.0, "shotsOnTarget": 2.0, "totalShots": 3.0, "totalGoals": 0.0}}, "salary": 5700}, {"id": "309563", "name": "L Ugochukwu", "position": "M", "displayName": "Lesley Ugochukwu", "jersey": "16", "citizen": "FRA", "stats": {"general": {"foulsCommitted": 3.0, "foulsSuffered": 2.0, "redCards": 0.0, "yellowCards": 2.0, "ownGoals": 0.0, "appearances": 10.0, "subIns": 7.0}, "offensive": {"goalAssists": 0.0, "offsides": 0.0, "shotsOnTarget": 0.0, "totalShots": 0.0, "totalGoals": 0.0}}, "salary": 5800}, {"id": "189007", "name": "R James", "position": "D", "displayName": "Reece James", "jersey": "24", "citizen": "ENG", "stats": {"general": {"foulsCommitted": 4.0, "foulsSuffered": 3.0, "redCards": 1.0, "yellowCards": 1.0, "ownGoals": 0.0, "appearances": 8.0, "subIns": 3.0}, "offensive": {"goalAssists": 1.0, "offsides": 0.0, "shotsOnTarget": 0.0, "totalShots": 7.0, "totalGoals": 0.0}}, "salary": 5700}, {"id": "282585", "name": "B Badiashile", "position": "D", "displayName": "Benoit Badiashile", "jersey": "5", "citizen": "FRA", "stats": {"general": {"foulsCommitted": 5.0, "foulsSuffered": 5.0, "redCards": 0.0, "yellowCards": 1.0, "ownGoals": 0.0, "appearances": 8.0, "subIns": 2.0}, "offensive": {"goalAssists": 1.0, "offsides": 0.0, "shotsOnTarget": 1.0, "totalShots": 3.0, "totalGoals": 0.0}}, "salary": 5700}, {"id": "222176", "name": "C Nkunku", "position": "F", "displayName": "Christopher Nkunku", "jersey": "18", "citizen": "FRA", "stats": {"general": {"foulsCommitted": 6.0, "foulsSuffered": 3.0, "redCards": 0.0, "yellowCards": 0.0, "ownGoals": 0.0, "appearances": 7.0, "subIns": 5.0}, "offensive": {"goalAssists": 0.0, "offsides": 1.0, "shotsOnTarget": 4.0, "totalShots": 10.0, "totalGoals": 2.0}}, "salary": 6200}, {"id": "294317", "name": "C Chukwuemeka", "position": "M", "displayName": "Carney Chukwuemeka", "jersey": "17", "citizen": "ENG", "stats": {"general": {"foulsCommitted": 2.0, "foulsSuffered": 1.0, "redCards": 0.0, "yellowCards": 2.0, "ownGoals": 0.0, "appearances": 6.0, "subIns": 4.0}, "offensive": {"goalAssists": 1.0, "offsides": 0.0, "shotsOnTarget": 2.0, "totalShots": 2.0, "totalGoals": 1.0}}, "salary": 6000}, {"id": "325536", "name": "A Gilchrist", "position": "D", "displayName": "Alfie Gilchrist", "jersey": "42", "citizen": "ENG", "stats": {"general": {"foulsCommitted": 1.0, "foulsSuffered": 0.0, "redCards": 0.0, "yellowCards": 0.0, "ownGoals": 0.0, "appearances": 5.0, "subIns": 5.0}, "offensive": {"goalAssists": 0.0, "offsides": 1.0, "shotsOnTarget": 0.0, "totalShots": 0.0, "totalGoals": 0.0}}, "salary": 5700}, {"id": "227784", "name": "T Chalobah", "position": "D", "displayName": "Trevoh Chalobah", "jersey": "14", "citizen": "ENG", "stats": {"general": {"foulsCommitted": 0.0, "foulsSuffered": 2.0, "redCards": 0.0, "yellowCards": 0.0, "ownGoals": 0.0, "appearances": 3.0, "subIns": 1.0}, "offensive": {"goalAssists": 0.0, "offsides": 0.0, "shotsOnTarget": 0.0, "totalShots": 0.0, "totalGoals": 0.0}}, "salary": 5200}, {"id": "336394", "name": "C Casadei", "position": "M", "displayName": "Cesare Casadei", "jersey": "31", "citizen": "ITA", "stats": {"general": {"foulsCommitted": 2.0, "foulsSuffered": 0.0, "redCards": 0.0, "yellowCards": 0.0, "ownGoals": 0.0, "appearances": 3.0, "subIns": 3.0}, "offensive": {"goalAssists": 0.0, "offsides": 0.0, "shotsOnTarget": 0.0, "totalShots": 0.0, "totalGoals": 0.0}}, "salary": 5500}, {"id": "308217", "name": "R Lavia", "position": "M", "displayName": "Romeo Lavia", "jersey": "45", "citizen": "BEL", "stats": {"general": {"foulsCommitted": 1.0, "foulsSuffered": 1.0, "redCards": 0.0, "yellowCards": 0.0, "ownGoals": 0.0, "appearances": 1.0, "subIns": 1.0}, "offensive": {"goalAssists": 0.0, "offsides": 0.0, "shotsOnTarget": 0.0, "totalShots": 0.0, "totalGoals": 0.0}}, "salary": 5500}, {"id": "361499", "name": "Deivid Washington", "position": "F", "displayName": "Deivid Washington", "jersey": "36", "citizen": "BRA", "stats": {"general": {"foulsCommitted": 0.0, "foulsSuffered": 0.0, "redCards": 0.0, "yellowCards": 0.0, "ownGoals": 0.0, "appearances": 1.0, "subIns": 1.0}, "offensive": {"goalAssists": 0.0, "offsides": 0.0, "shotsOnTarget": 0.0, "totalShots": 1.0, "totalGoals": 0.0}}, "salary": 5700}, {"id": "177545", "name": "M Bettinelli", "position": "G", "displayName": "Marcus Bettinelli", "jersey": "13", "citizen": "ENG", "stats": {"general": {"foulsCommitted": 0.0, "foulsSuffered": 0.0, "redCards": 0.0, "yellowCards": 1.0, "ownGoals": 0.0, "appearances": 0.0, "subIns": 0.0}, "offensive": {"goalAssists": 0.0, "offsides": 0.0, "shotsOnTarget": 0.0, "totalShots": 0.0, "totalGoals": 0.0}}, "salary": 4800}, {"id": "325540", "name": "J Brooking", "position": "D", "displayName": "Josh Brooking", "jersey": "44", "citizen": "ENG", "stats": {"general": {"foulsCommitted": 0.0, "foulsSuffered": 0.0, "redCards": 0.0, "yellowCards": 0.0, "ownGoals": 0.0, "appearances": 0.0, "subIns": 0.0}, "offensive": {"goalAssists": 0.0, "offsides": 0.0, "shotsOnTarget": 0.0, "totalShots": 0.0, "totalGoals": 0.0}}, "salary": 5200}, {"id": "349102", "name": "I Samuels-Smith", "position": "D", "displayName": "Ish\u00e9 Samuels-Smith", "jersey": "53", "citizen": "ENG", "stats": {"general": {"foulsCommitted": 0.0, "foulsSuffered": 0.0, "redCards": 0.0, "yellowCards": 0.0, "ownGoals": 0.0, "appearances": 0.0, "subIns": 0.0}, "offensive": {"goalAssists": 0.0, "offsides": 0.0, "shotsOnTarget": 0.0, "totalShots": 0.0, "totalGoals": 0.0}}, "salary": 5200}, {"id": "368317", "name": "J Acheampong", "position": "D", "displayName": "Josh Acheampong", "jersey": "63", "citizen": "ENG", "stats": {"general": {"foulsCommitted": 0.0, "foulsSuffered": 0.0, "redCards": 0.0, "yellowCards": 0.0, "ownGoals": 0.0, "appearances": 0.0, "subIns": 0.0}, "offensive": {"goalAssists": 0.0, "offsides": 0.0, "shotsOnTarget": 0.0, "totalShots": 0.0, "totalGoals": 0.0}}, "salary": 5200}, {"id": "345762", "name": "J Tauriainen", "position": "M", "displayName": "Jimi Tauriainen", "jersey": "49", "citizen": "FIN", "stats": {"general": {"foulsCommitted": 0.0, "foulsSuffered": 0.0, "redCards": 0.0, "yellowCards": 0.0, "ownGoals": 0.0, "appearances": 0.0, "subIns": 0.0}, "offensive": {"goalAssists": 0.0, "offsides": 0.0, "shotsOnTarget": 0.0, "totalShots": 0.0, "totalGoals": 0.0}}, "salary": 5500}, {"id": "347314", "name": "L Castledine", "position": "M", "displayName": "Leo Castledine", "jersey": "54", "citizen": "ENG", "stats": {"general": {"foulsCommitted": 0.0, "foulsSuffered": 0.0, "redCards": 0.0, "yellowCards": 0.0, "ownGoals": 0.0, "appearances": 0.0, "subIns": 0.0}, "offensive": {"goalAssists": 0.0, "offsides": 0.0, "shotsOnTarget": 0.0, "totalShots": 0.0, "totalGoals": 0.0}}, "salary": 5500}, {"id": "374222", "name": "O Harrison", "position": "M", "displayName": "Ollie Harrison", "jersey": "79", "citizen": "ENG", "stats": {"general": {"foulsCommitted": 0.0, "foulsSuffered": 0.0, "redCards": 0.0, "yellowCards": 0.0, "ownGoals": 0.0, "appearances": 0.0, "subIns": 0.0}, "offensive": {"goalAssists": 0.0, "offsides": 0.0, "shotsOnTarget": 0.0, "totalShots": 0.0, "totalGoals": 0.0}}, "salary": 5500}, {"id": "340678", "name": "D Moreira", "position": "F", "displayName": "Diego Moreira", "jersey": "43", "citizen": "POR", "stats": {"general": {"foulsCommitted": 0.0, "foulsSuffered": 0.0, "redCards": 0.0, "yellowCards": 0.0, "ownGoals": 0.0, "appearances": 0.0, "subIns": 0.0}, "offensive": {"goalAssists": 0.0, "offsides": 0.0, "shotsOnTarget": 0.0, "totalShots": 0.0, "totalGoals": 0.0}}, "salary": 5700}, {"id": "366999", "name": "R Stutter", "position": "F", "displayName": "Ronnie Stutter", "jersey": "62", "citizen": "ENG", "stats": {"general": {"foulsCommitted": 0.0, "foulsSuffered": 0.0, "redCards": 0.0, "yellowCards": 0.0, "ownGoals": 0.0, "appearances": 0.0, "subIns": 0.0}, "offensive": {"goalAssists": 0.0, "offsides": 0.0, "shotsOnTarget": 0.0, "totalShots": 0.0, "totalGoals": 0.0}}, "salary": 5700}]